[
  {
    "name": "Morango", "description":"Morangos irresistíveis e sem veneno da fazenda Fresamor",
    "price":"8.50" ,"unit_measurement":"Bandeja", "url": "https://res.cloudinary.com/da6ufv8ct/image/upload/v1600979311/ep0quh2x4q79628r51sudt3urfoq.jpg"
  },
  {
    "name": "Kiwi", "description":"Frutas selecionadas" ,
    "price":"7.80" ,"unit_measurement":"500g", "url": "https://res.cloudinary.com/da6ufv8ct/image/upload/v1600979535/6xqd6fdfic5vsfw44h4v85k9994h.jpg"
  },
  {
    "name": "Banana Prata", "description":"Potássio garantido para prevenção de cãibras durante a realização de exercícios físicos" ,
    "price":"7.80" , "unit_measurement":"Kg", "url": "https://res.cloudinary.com/da6ufv8ct/image/upload/v1600979671/n9pr95du6szmikwgqc8j9utzy0gq.jpg"
  },
  {
    "name": "Melancia", "description":"Muito saborosa" ,
    "price":"10" ,"unit_measurement":"Unidade", "url": "https://res.cloudinary.com/da6ufv8ct/image/upload/v1600978675/rw0cu2ifvun1f58dvjl5r4ypcmp0.jpg"
  },
  {
    "name": "Abrobinha", "description":"Legumes e verduras" ,
    "price":"7" ,"unit_measurement":"Kg", "url": "https://res.cloudinary.com/da6ufv8ct/image/upload/v1600978815/kf0e05a74ksfit6b7j4g8hwstvrg.jpg"
  },
  {
    "name": "Alho", "description":"Legumes e verduras" ,
    "price":"15.50" ,"unit_measurement":"200 gramas", "url": "https://res.cloudinary.com/da6ufv8ct/image/upload/v1600978885/e1i37xiu4nl9qpbgs1kn86iayjk5.jpg"
  },
  {
    "name": "Tomate", "description":"Tomate italiano" ,
    "price":"15.50" ,"unit_measurement":"Kg", "url": "https://res.cloudinary.com/da6ufv8ct/image/upload/v1600978866/nz4fyiqw8z9keqb8svofsl71vhh5.jpg"
  },
  {
    "name": "Abacate", "description":"Fruto rico em proteínas, fósforo, ferro, gorduras, fibras, potássio e diversas vitaminas." ,
    "price":"10" ,"unit_measurement":"Kg", "url": "https://res.cloudinary.com/da6ufv8ct/image/upload/v1600978989/03xmjfnclu51kp2offgkp52ravg1.jpg"
  },
  {
    "name": "Cebolinha", "description":"Ervas e Temperos." ,
    "price":"4.50" ,"unit_measurement":"Maço", "url": "https://res.cloudinary.com/da6ufv8ct/image/upload/v1600978951/q6rlakxjp8n16oi3bca6hh40tc48.jpg"
  },
  {
    "name": "Abacaxi", "description":"As quantidades de fibra, potássio e vitamina C presentes no abacaxi ajudam a diminuir os níveis de colesterol ruim no organismo." ,
    "price":"10" ,"unit_measurement":"Unidade", "url": "https://res.cloudinary.com/da6ufv8ct/image/upload/v1600978822/ewbhcp6za9fh1e4h1r1jg8cuxz7n.jpg"
  }
]
